snakesay_project_2/__init__.py
snakesay_project_2/__main__.py
snakesay_project_2/main.py
snakesay_project_2-0.1.0.dist-info/METADATA
snakesay_project_2-0.1.0.dist-info/WHEEL
snakesay_project_2-0.1.0.dist-info/entry_points.txt
snakesay_project_2-0.1.0.dist-info/top_level.txt
snakesay_project_2-0.1.0.dist-info/RECORD
