Metadata-Version: 2.4
Name: snakesay_project_2
Version: 0.1.0
Summary: Add your description here
Requires-Python: >=3.13
Requires-Dist: pandas>=2.2.3
